Workbook

Sheet 2025 Budget
B1: THE PURPLE PORTFOLIO | 2025 BUDGET PLANNER
A2: Planner answers auto-populate this sheet. Override any cell freely to personalise.
A3: LIFE STAGE | C3: Student | H3: BIRTH YEAR | I3: 2000 | K3: ✓ PLANNER SYNC ACTIVE — override any cell to customise | P3: =IFERROR(MATCH(C3,{"Student","Young Professional","Family","Mid-Career","Retirement"},0),1)
A5: CATEGORY | C5: JAN | D5: FEB | E5: MAR | F5: APR | G5: MAY | H5: JUN | I5: JUL | J5: AUG | K5: SEP | L5: OCT | M5: NOV | N5: DEC | O5: ANNUAL
A6: ▶ INCOME
A7: =CHOOSE($P$3,"Part-time / OSAP","Salary / Wages","Primary Salary","Primary Salary","CPP") | O7: =SUM(C7:N7)
A8: =CHOOSE($P$3,"Bursaries / Grants","Side Income / Freelance","Partner Salary","Bonus / Commission","OAS / GIS") | O8: =SUM(C8:N8)
A9: =CHOOSE($P$3,"Other Income","Investment Income","Child Benefits (CCB)","Rental Income","RRIF Withdrawals") | O9: =SUM(C9:N9)
A10: =CHOOSE($P$3,"","Other Income","Investment Income","Investment / Dividends","Investment Dividends / Income") | O10: =SUM(C10:N10)
A11: =CHOOSE($P$3,"","","Other","Business Income","Pension") | O11: =SUM(C11:N11)
A12: =CHOOSE($P$3,"","","","Other","Other") | O12: =SUM(C12:N12)
A13: TOTAL INCOME | C13: =SUM(C7:C12) | D13: =SUM(D7:D12) | E13: =SUM(E7:E12) | F13: =SUM(F7:F12) | G13: =SUM(G7:G12) | H13: =SUM(H7:H12) | I13: =SUM(I7:I12) | J13: =SUM(J7:J12) | ... N13: =SUM(N7:N12) | O13: =SUM(C13:N13)
A15: ▶ EXPENSES
A16: =CHOOSE($P$3,"Rent / Housing","Rent / Mortgage","Mortgage / Rent","Mortgage","Housing / Maintenance") | O16: =SUM(C16:N16)
A17: =CHOOSE($P$3,"Groceries","Groceries","Childcare / School","Property Tax","Healthcare / Prescriptions") | O17: =SUM(C17:N17)
A18: =CHOOSE($P$3,"Phone / Internet","Transportation","Groceries","Travel / Leisure","Travel / Leisure") | O18: =SUM(C18:N18)
A19: =CHOOSE($P$3,"Transportation","Phone / Internet","Transportation","Insurance (Life/Property)","Groceries") | O19: =SUM(C19:N19)
A20: =CHOOSE($P$3,"Tuition / Books","Dining / Social","Utilities","Healthcare / Dental","Utilities") | O20: =SUM(C20:N20)
A21: =CHOOSE($P$3,"Student Loan Payment","Subscriptions","Insurance (Life/Health)","Dining / Entertainment","Insurance") | O21: =SUM(C21:N21)
A22: =CHOOSE($P$3,"Entertainment","Health / Fitness","Travel / Activities","Subscriptions","Estate / Legal Fees") | O22: =SUM(C22:N22)
A23: =CHOOSE($P$3,"","Savings","Subscriptions","Children's Education","Charitable Giving") | O23: =SUM(C23:N23)
A24: =CHOOSE($P$3,"","","Healthcare","Charitable Giving","") | O24: =SUM(C24:N24)
A25: TOTAL EXPENSES | C25: =SUM(C16:C24) | D25: =SUM(D16:D24) | E25: =SUM(E16:E24) | F25: =SUM(F16:F24) | G25: =SUM(G16:G24) | H25: =SUM(H16:H24) | I25: =SUM(I16:I24) | J25: =SUM(J16:J24) | ... N25: =SUM(N16:N24) | O25: =SUM(C25:N25)
A27: ▶ INVESTMENTS & SAVINGS
A28: =CHOOSE($P$3,"TFSA","TFSA","RRSP","RRSP","RRIF") | O28: =SUM(C28:N28)
A29: =CHOOSE($P$3,"FHSA","FHSA","TFSA","TFSA","TFSA") | O29: =SUM(C29:N29)
A30: =CHOOSE($P$3,"Emergency Fund","RRSP","RESP","Non-Registered","Non-Registered") | O30: =SUM(C30:N30)
A31: =CHOOSE($P$3,"","Emergency Fund","Non-Registered","Real Estate","Charitable Giving") | O31: =SUM(C31:N31)
A32: =CHOOSE($P$3,"","","Emergency Fund","Business Investments","") | O32: =SUM(C32:N32)
A33: =CHOOSE($P$3,"","","","Emergency Fund","") | O33: =SUM(C33:N33)
A34: TOTAL INVESTMENTS | C34: =SUM(C28:C33) | D34: =SUM(D28:D33) | E34: =SUM(E28:E33) | F34: =SUM(F28:F33) | G34: =SUM(G28:G33) | H34: =SUM(H28:H33) | I34: =SUM(I28:I33) | J34: =SUM(J28:J33) | ... N34: =SUM(N28:N33) | O34: =SUM(C34:N34)
A36: NET CASH FLOW | C36: =C13-C25-C34 | D36: =D13-D25-D34 | E36: =E13-E25-E34 | F36: =F13-F25-F34 | G36: =G13-G25-G34 | H36: =H13-H25-H34 | I36: =I13-I25-I34 | J36: =J13-J25-J34 | ... O36: =O13-O25-O34
A38: ⟵ PLANNER SYNC — Fields below are auto-loaded from the Planner tab. Override freely.
A39: Monthly Income | E39: =O13/12
A40: Monthly Expenses | E40: =O25/12
A41: Monthly Savings | E41: =O34/12
A42: Life Stage | E42: =C3

Sheet Future Year
B1: THE PURPLE PORTFOLIO | FUTURE YEAR PROJECTIONS
A2: Project finances forward. Adjust % changes or hard-code any projected value directly.
A3: PROJECTED YEAR | B3: 2026 | C3: AUTO LIFE STAGE → | D3: =IF('2025 Budget'!I3="","—",IF(B3-'2025 Budget'!I3<25,"Student",IF(B3-'2025 Budget'!I3<35,"Young Professional",IF(B3-'2025 Budget'!I3<50,"Family",IF(B3-'2025 Budget'!I3<65,"Mid-Career","Retirement")))))
A5: ▶ YEAR-OVER-YEAR % CHANGE ASSUMPTIONS
A6: Category | B6: YoY % Change | C6: Override ($) | D6: Use Override? | E6: 2025 Actual | F6: Projected | G6: Change ($) | H6: Notes
A7: Total Income | B7: 0.04 | D7: N | E7: ='2025 Budget'!O13 | F7: =IF(D7="Y",C7,E7*(1+B7)^(B3-2025)) | G7: =F7-E7 | H7: Income grows with career stage
A8: Total Expenses | B8: 0.03 | D8: N | E8: ='2025 Budget'!O25 | F8: =IF(D8="Y",C8,E8*(1+B8)^(B3-2025)) | G8: =F8-E8 | H8: CPI + lifestyle inflation
A9: Total Investments | B9: 0.05 | D9: N | E9: ='2025 Budget'!O34 | F9: =IF(D9="Y",C9,E9*(1+B9)^(B3-2025)) | G9: =F9-E9 | H9: Increasing contributions
A10: Net Cash Flow | B10: 0.02 | D10: N | E10: ='2025 Budget'!O36 | F10: =IF(D10="Y",C10,E10*(1+B10)^(B3-2025)) | G10: =F10-E10 | H10: Income − expenses − investments
A12: ▶ MULTI-YEAR FINANCIAL PROJECTION (2025 – 2035)
A13: Category | B13: 2025 | C13: 2026 | D13: 2027 | E13: 2028 | F13: 2029 | G13: 2030 | H13: 2031 | I13: 2032 | J13: 2033 | K13: 2034 | L13: 2035
A14: Income | B14: ='2025 Budget'!O13 | C14: =B14*(1+B7)^1 | D14: =B14*(1+B7)^2 | E14: =B14*(1+B7)^3 | F14: =B14*(1+B7)^4 | G14: =B14*(1+B7)^5 | H14: =B14*(1+B7)^6 | I14: =B14*(1+B7)^7 | J14: =B14*(1+B7)^8 | K14: =B14*(1+B7)^9 | L14: =B14*(1+B7)^10
A15: Expenses | B15: ='2025 Budget'!O25 | C15: =B15*(1+B8)^1 | D15: =B15*(1+B8)^2 | E15: =B15*(1+B8)^3 | F15: =B15*(1+B8)^4 | G15: =B15*(1+B8)^5 | H15: =B15*(1+B8)^6 | I15: =B15*(1+B8)^7 | J15: =B15*(1+B8)^8 | K15: =B15*(1+B8)^9 | L15: =B15*(1+B8)^10
A16: Investments | B16: ='2025 Budget'!O34 | C16: =B16*(1+B9)^1 | D16: =B16*(1+B9)^2 | E16: =B16*(1+B9)^3 | F16: =B16*(1+B9)^4 | G16: =B16*(1+B9)^5 | H16: =B16*(1+B9)^6 | I16: =B16*(1+B9)^7 | J16: =B16*(1+B9)^8 | K16: =B16*(1+B9)^9 | L16: =B16*(1+B9)^10
A17: Net CF | B17: ='2025 Budget'!O36 | C17: =B17*(1+B10)^1 | D17: =B17*(1+B10)^2 | E17: =B17*(1+B10)^3 | F17: =B17*(1+B10)^4 | G17: =B17*(1+B10)^5 | H17: =B17*(1+B10)^6 | I17: =B17*(1+B10)^7 | J17: =B17*(1+B10)^8 | K17: =B17*(1+B10)^9 | L17: =B17*(1+B10)^10
A18: Auto Life Stage | B18: =IF('2025 Budget'!I3="","—",IF(2025-'2025 Budget'!I3<25,"Student",IF(2025-'2025 Budget'!I3<35,"Young Pro",IF(2025-'2025 Budget'!I3<50,"Family",IF(2025-'2025 Budget'!I3<65,"Mid-Career","Retirement"))))) | C18: =IF('2025 Budget'!I3="","—",IF(2026-'2025 Budget'!I3<25,"Student",IF(2026-'2025 Budget'!I3<35,"Young Pro",IF(2026-'2025 Budget'!I3<50,"Family",IF(2026-'2025 Budget'!I3<65,"Mid-Career","Retirement"))))) | D18: =IF('2025 Budget'!I3="","—",IF(2027-'2025 Budget'!I3<25,"Student",IF(2027-'2025 Budget'!I3<35,"Young Pro",IF(2027-'2025 Budget'!I3<50,"Family",IF(2027-'2025 Budget'!I3<65,"Mid-Career","Retirement"))))) | E18: =IF('2025 Budget'!I3="","—",IF(2028-'2025 Budget'!I3<25,"Student",IF(2028-'2025 Budget'!I3<35,"Young Pro",IF(2028-'2025 Budget'!I3<50,"Family",IF(2028-'2025 Budget'!I3<65,"Mid-Career","Retirement"))))) | F18: =IF('2025 Budget'!I3="","—",IF(2029-'2025 Budget'!I3<25,"Student",IF(2029-'2025 Budget'!I3<35,"Young Pro",IF(2029-'2025 Budget'!I3<50,"Family",IF(2029-'2025 Budget'!I3<65,"Mid-Career","Retirement"))))) | G18: =IF('2025 Budget'!I3="","—",IF(2030-'2025 Budget'!I3<25,"Student",IF(2030-'2025 Budget'!I3<35,"Young Pro",IF(2030-'2025 Budget'!I3<50,"Family",IF(2030-'2025 Budget'!I3<65,"Mid-Career","Retirement"))))) | H18: =IF('2025 Budget'!I3="","—",IF(2031-'2025 Budget'!I3<25,"Student",IF(2031-'2025 Budget'!I3<35,"Young Pro",IF(2031-'2025 Budget'!I3<50,"Family",IF(2031-'2025 Budget'!I3<65,"Mid-Career","Retirement"))))) | I18: =IF('2025 Budget'!I3="","—",IF(2032-'2025 Budget'!I3<25,"Student",IF(2032-'2025 Budget'!I3<35,"Young Pro",IF(2032-'2025 Budget'!I3<50,"Family",IF(2032-'2025 Budget'!I3<65,"Mid-Career","Retirement"))))) | J18: =IF('2025 Budget'!I3="","—",IF(2033-'2025 Budget'!I3<25,"Student",IF(2033-'2025 Budget'!I3<35,"Young Pro",IF(2033-'2025 Budget'!I3<50,"Family",IF(2033-'2025 Budget'!I3<65,"Mid-Career","Retirement"))))) | K18: =IF('2025 Budget'!I3="","—",IF(2034-'2025 Budget'!I3<25,"Student",IF(2034-'2025 Budget'!I3<35,"Young Pro",IF(2034-'2025 Budget'!I3<50,"Family",IF(2034-'2025 Budget'!I3<65,"Mid-Career","Retirement"))))) | L18: =IF('2025 Budget'!I3="","—",IF(2035-'2025 Budget'!I3<25,"Student",IF(2035-'2025 Budget'!I3<35,"Young Pro",IF(2035-'2025 Budget'!I3<50,"Family",IF(2035-'2025 Budget'!I3<65,"Mid-Career","Retirement")))))
A20: ▶ LIFE EVENTS (one-time adjustments)
A21: Year | B21: Event | C21: Income Impact | D21: Expense Impact | E21: Notes

Sheet Life Stage Guide
B1: LIFE STAGE GUIDE | THE PURPLE PORTFOLIO
A2: Reference guide for budget personalisation and life-stage transitions
A4: Life Stage | B4: Key Income Sources | C4: Key Expenses | D4: Key Accounts
A5: Student | B5: Part-time work OSAP / student loans Bursaries & grants | C5: Rent, groceries, phone Tuition & books Student loan payments | D5: TFSA, FHSA Emergency fund
A6: Young Professional | B6: Salary / wages Side income / freelance Investment income | C6: Rent/mortgage, transport Dining & subscriptions Health & fitness | D6: TFSA, FHSA, RRSP
A7: Family | B7: Dual income Child benefits (CCB) Investment income | C7: Mortgage, childcare Utilities, travel Insurance | D7: RRSP, TFSA, RESP Non-registered
A8: Mid-Career | B8: Peak salary & bonuses Rental / business income Investment dividends | C8: Mortgage, property tax Travel, insurance Life insurance premium | D8: RRSP max, TFSA Non-reg, real estate Business investments
A9: Retirement | B9: CPP, OAS, pension RRIF withdrawals Investment dividends | C9: Housing, healthcare Travel & leisure Estate / legal fees | D9: RRIF, TFSA Non-registered Charitable giving

Sheet Claude — Dev Instructions
A1: 🛠 Claude Dev Instructions | Purple Portfolio Budget (FINAL v5)
A2: OVERVIEW | B2: Purple Portfolio — three core tabs: PLANNER → BUDGET → LIBRARY The Planner is the ENTRY POINT. The Budget auto-populates FROM the Planner. Data flow is strictly one-way: Planner writes → Budget reads. Budget never writes back to Planner.
A4: DATA FLOW | B4: 1. User completes PLANNER tab (income, expenses, goals, life stage, birth year). 2. Planner stores to localStorage: budget_monthly_income | budget_monthly_expenses | budget_monthly_savings budget_life_stage | budget_birth_year 3. On Budget tab mount: read localStorage, pre-fill matching rows. 4. Show a dismissible banner: '✓ Planner data loaded — override any field to customise' 5. User overrides stay only in Budget. If Planner is updated, a 'Refresh from Planner' button re-syncs.
A6: EXCEL EXPORT | B6: Include a prominent Export to Excel button (top-right of Budget tab). Use SheetJS (client-side, no server needed). Export filename: PurplePortfolio_Budget_[Year].xlsx Export 3 sheets: '2025 Budget', 'Future Year', 'Life Stage Guide'. Match styling: dark purple headers, gold text, ivy green net cash flow row. Both paths must work: use website OR download Excel — same data, different format.
A8: BUDGET TAB LAYOUT | B8: Desktop-first (min-width 1280px). Mobile is secondary (collapsible months). Header: Logo (top-left, 44px), Title, Life Stage dropdown, Birth Year input. No sticky/frozen panes — user scrolls through the full budget. Stacked vertically: INCOME → EXPENSES → INVESTMENTS → NET CASH FLOW. Columns: Category | Jan | Feb | Mar | Apr | May | Jun | Jul | Aug | Sep | Oct | Nov | Dec | Annual Input cells: large (min 48px row height, 100px col width, 16px font). Annual column: auto-sum of Jan-Dec (read-only, styled differently). Net Cash Flow row: Income − Expenses − Investments. Ivy green background, white text.
A10: LIFE STAGE FILTER | B10: Dropdown with 5 options: Student | Young Professional | Family | Mid-Career | Retirement THIS IS A TEMPLATE SWAP — not a cosmetic label change. Changing life stage replaces the entire set of row labels AND row count for Income, Expenses, Investments. Show a confirm dialog before switching ('Switch life stage? Your entered amounts will be kept, labels will update.') Complexity scales up with life stage: Student: 3 income rows, 7 expense rows, 3 investment rows (simple, clean) Young Pro: 4 income, 8 expense, 4 investment Family: 5 income, 9 expense, 5 investment Mid-Career: 6 income, 9 expense, 6 investment (capital-returning assets, rental, business) Retirement: 6 income, 8 expense, 4 investment (CPP, OAS, RRIF, dividends) Include a '+ Add row' button at the bottom of each section to let users add custom rows. See Life Stage Guide sheet for exact row labels per stage.
A12: STAGE ROW LABELS | B12: STUDENT — Income: Part-time/OSAP, Bursaries/Grants, Other Expenses: Rent/Housing, Groceries, Phone/Internet, Transportation, Tuition/Books, Student Loan, Entertainment Invest: TFSA, FHSA, Emergency Fund YOUNG PRO — Income: Salary, Side Income, Investment Income, Other Expenses: Rent/Mortgage, Groceries, Transportation, Phone/Internet, Dining/Social, Subscriptions, Health/Fitness, Savings Invest: TFSA, FHSA, RRSP, Emergency Fund FAMILY — Income: Primary Salary, Partner Salary, CCB, Investment Income, Other Expenses: Mortgage/Rent, Childcare/School, Groceries, Transportation, Utilities, Insurance, Travel/Activities, Subscriptions, Healthcare Invest: RRSP, TFSA, RESP, Non-Registered, Emergency Fund MID-CAREER — Income: Salary, Bonus/Commission, Rental Income, Dividends, Business Income, Other Expenses: Mortgage, Property Tax, Travel/Leisure, Insurance, Healthcare, Dining, Subscriptions, Children's Education, Charitable Giving Invest: RRSP, TFSA, Non-Registered, Real Estate, Business Investments, Emergency Fund RETIREMENT — Income: CPP, OAS/GIS, RRIF Withdrawals, Dividends/Income, Pension, Other Expenses: Housing/Maintenance, Healthcare, Travel/Leisure, Groceries, Utilities, Insurance, Estate/Legal Fees, Charitable Giving Invest: RRIF, TFSA, Non-Registered, Charitable Giving
A14: FUTURE YEAR TAB | B14: Year selector: dropdown 2026–2035. Auto Life Stage: calculated from birth year + selected year (same age-band logic as Budget tab). % Change table: 4 rows (Income, Expenses, Investments, Net CF) with YoY% | Override | Use Override? | 2025 Actual | Projected | Change ($) | Notes Multi-year projection TABLE (2025–2035): rows = Income, Expenses, Investments, Net CF. Cols = each year. 2025 column = pulled from Budget tab totals (read-only). 2026+ = compound growth: 2025_actual * (1 + pct)^(year-2025) — live-updates when % changes. Override column: user can type any number for any year cell and toggle 'Y' to use it. Auto Life Stage row beneath table: shows projected life stage per year. Life Events table: Year | Event | Income Impact | Expense Impact | Notes — 5 editable rows. Bar chart: Income / Expenses / Net CF per year, 2025–2035. Colours: purple / red / ivy green. Chart must only have 3 series — no phantom/empty series. Bind directly to the 3 data rows.
A16: STYLING | B16: Background: #1A0A2E (deep dark purple) for headers/hero areas. Section headers: #3B1F6A (mid purple) background, #B8972E gold text. Input rows: alternating #EDE9F6 (pale purple) and #F5F3FF (off-white). Income section: pale purple rows. Expense section: very light red #FFF0F0 rows. Investment section: very light green #F0FFF4 rows. Net Cash Flow row: #2D6A4F (ivy green) background, white text. Gold accent: #B8972E / #D4AF37 — used for column headers and highlights. NO bright/neon yellow — gold only. Borders: solid #3B1F6A, never fading to white. Every data region has a clear solid border box. Logo: 44×44px, top-left corner of every sheet. No extra whitespace around it. Font: system-ui / Inter / Calibri, 16px for inputs, 14px for labels, 12px for sub-labels. Desktop-first: monthly columns ≥100px, row heights ≥48px for data rows.
A18: MOBILE | B18: On screens <768px: collapse month columns into a single 'Monthly Avg' column. Show Jan-Dec toggle button to expand to full grid. Sticky header row with category names. Life stage dropdown becomes a bottom sheet on mobile.
A20: UX NOTES | B20: '+ Add row' button at bottom of each section (Income, Expenses, Investments). Row labels are editable (click to rename). Planner Sync banner: top of Budget, dismissible, shows 4 synced values. Export to Excel button: top-right, uses SheetJS, filename PurplePortfolio_Budget_[Year].xlsx Auto-save to localStorage on every input change. Tooltips on investment account names (explain TFSA, FHSA, RRSP, RESP, RRIF briefly).
